djangocms_lightgallery/__init__.py
djangocms_lightgallery/admin.py
djangocms_lightgallery/apps.py
djangocms_lightgallery/cms_plugins.py
djangocms_lightgallery/models.py
djangocms_lightgallery/settings.py
djangocms_lightgallery/urls.py
djangocms_lightgallery/views.py
djangocms_lightgallery/migrations/0001_initial.py
djangocms_lightgallery/migrations/__init__.py
djangocms_lightgallery/static/css/djangocms_lightgallery.css
djangocms_lightgallery/static/js/djangocms_lightgallery.js
djangocms_lightgallery/static/lightGallery/css/lg-fb-comment-box.css
djangocms_lightgallery/static/lightGallery/css/lg-fb-comment-box.min.css
djangocms_lightgallery/static/lightGallery/css/lg-transitions.css
djangocms_lightgallery/static/lightGallery/css/lg-transitions.min.css
djangocms_lightgallery/static/lightGallery/css/lightgallery.css
djangocms_lightgallery/static/lightGallery/css/lightgallery.min.css
djangocms_lightgallery/static/lightGallery/fonts/lg.eot
djangocms_lightgallery/static/lightGallery/fonts/lg.svg
djangocms_lightgallery/static/lightGallery/fonts/lg.ttf
djangocms_lightgallery/static/lightGallery/fonts/lg.woff
djangocms_lightgallery/static/lightGallery/img/loading.gif
djangocms_lightgallery/static/lightGallery/img/video-play.png
djangocms_lightgallery/static/lightGallery/img/vimeo-play.png
djangocms_lightgallery/static/lightGallery/img/youtube-play.png
djangocms_lightgallery/static/lightGallery/js/lightgallery-all.js
djangocms_lightgallery/static/lightGallery/js/lightgallery-all.min.js
djangocms_lightgallery/static/lightGallery/js/lightgallery.js
djangocms_lightgallery/static/lightGallery/js/lightgallery.min.js
djangocms_lightgallery/static/lightGallery/js/modules/lg-autoplay.js
djangocms_lightgallery/static/lightGallery/js/modules/lg-autoplay.min.js
djangocms_lightgallery/static/lightGallery/js/modules/lg-fullscreen.js
djangocms_lightgallery/static/lightGallery/js/modules/lg-fullscreen.min.js
djangocms_lightgallery-0.1.12.dist-info/DESCRIPTION.rst
djangocms_lightgallery-0.1.12.dist-info/METADATA
djangocms_lightgallery-0.1.12.dist-info/RECORD
djangocms_lightgallery-0.1.12.dist-info/WHEEL
djangocms_lightgallery-0.1.12.dist-info/metadata.json
djangocms_lightgallery-0.1.12.dist-info/top_level.txt
