Metadata-Version: 2.0
Name: djangocms-lightgallery
Version: 0.1.12
Summary: DjangoCMS Plugin for LighGallery library
Home-page: https://github.com/oesah/djangocms-lightgallery
Author: Özer Sahin
Author-email: o.sahin@oesah.de
License: MIT
Keywords: djangocms-lightgallery
Platform: UNKNOWN
Classifier: Development Status :: 3 - Alpha
Classifier: Framework :: Django
Classifier: Framework :: Django :: 1.8
Classifier: Framework :: Django :: 1.9
Classifier: Framework :: Django :: 1.10
Classifier: Intended Audience :: Developers
Classifier: License :: OSI Approved :: BSD License
Classifier: Natural Language :: English
Classifier: Programming Language :: Python :: 2
Classifier: Programming Language :: Python :: 2.7
Classifier: Programming Language :: Python :: 3
Classifier: Programming Language :: Python :: 3.3
Classifier: Programming Language :: Python :: 3.4
Classifier: Programming Language :: Python :: 3.5
Requires-Dist: django-filer
Requires-Dist: jsonfield
